{"IcoMoonType":"selection","icons":[{"icon":{"paths":["M972.8 512l-307.2-256v153.6h-358.4v204.8h358.4v153.6l307.2-256zM153.6 153.6h409.6v-102.4h-409.6c-56.32 0-102.4 46.080-102.4 102.4v716.8c0 56.32 46.080 102.4 102.4 102.4h409.6v-102.4h-409.6v-716.8z"],"attrs":[{}],"isMulticolor":false,"isMulticolor2":false,"grid":0,"tags":["logout"]},"attrs":[{}],"properties":{"order":2,"id":0,"name":"logout","prevSize":32,"code":59648},"setIdx":0,"setId":2,"iconIdx":0}],"height":1024,"metadata":{"name":"icomoon"},"preferences":{"showGlyphs":true,"showQuickUse":true,"showQuickUse2":true,"showSVGs":true,"fontPref":{"prefix":"icon-","metadata":{"fontFamily":"icomoon","majorVersion":1,"minorVersion":0},"metrics":{"emSize":1024,"baseline":6.25,"whitespace":50},"embed":false,"noie8":true,"ie7":false},"imagePref":{"prefix":"icon-","png":true,"useClassSelector":true,"color":0,"bgColor":16777215,"classSelector":".icon"},"historySize":50,"showCodes":true,"gridSize":16}}